adifas/__init__.py
adifas/cli.py
adifas-0.1.1.dist-info/LICENSE
adifas-0.1.1.dist-info/METADATA
adifas-0.1.1.dist-info/WHEEL
adifas-0.1.1.dist-info/entry_points.txt
adifas-0.1.1.dist-info/RECORD
